chum/__init__.py
chum/image.py
chum-0.0.1.dist-info/LICENSE
chum-0.0.1.dist-info/METADATA
chum-0.0.1.dist-info/WHEEL
chum-0.0.1.dist-info/top_level.txt
chum-0.0.1.dist-info/RECORD
