Metadata-Version: 2.1
Name: chum
Version: 0.0.1
Summary: Utilities for data preprocessing for ML/DL
Home-page: https://github.com/soham96/chum
Author: Soham Chatterjee
Author-email: 96soham96@gmail.com
License: UNKNOWN
Platform: UNKNOWN
Classifier: Programming Language :: Python :: 3.5
Classifier: License :: OSI Approved :: GNU General Public License v3 (GPLv3)
Classifier: Operating System :: OS Independent
